execjs/__init__.py
execjs/__main__.py
execjs/_abstract_runtime.py
execjs/_abstract_runtime_context.py
execjs/_exceptions.py
execjs/_external_runtime.py
execjs/_json2.py
execjs/_misc.py
execjs/_pyv8runtime.py
execjs/_runner_sources.py
execjs/_runtimes.py
execjs/runtime_names.py
PyExecJS2-1.6.1.dist-info/LICENSE
PyExecJS2-1.6.1.dist-info/METADATA
PyExecJS2-1.6.1.dist-info/WHEEL
PyExecJS2-1.6.1.dist-info/top_level.txt
PyExecJS2-1.6.1.dist-info/RECORD
