Metadata-Version: 2.1
Name: PyExecJS2
Version: 1.6.1
Summary: Run JavaScript code from Python
Home-page: https://github.com/meatjam/PyExecJS
Author: meatjam
Author-email: 
License: MIT License
Platform: UNKNOWN
Classifier: Development Status :: 5 - Production/Stable
Classifier: Intended Audience :: Developers
Classifier: Natural Language :: English
Classifier: License :: OSI Approved :: MIT License
Classifier: Programming Language :: Python
Classifier: Programming Language :: Python :: 2
Classifier: Programming Language :: Python :: 2.7
Classifier: Programming Language :: Python :: 3
Classifier: Programming Language :: Python :: 3.3
Classifier: Programming Language :: Python :: 3.4
Classifier: Programming Language :: Python :: 3.5
Classifier: Programming Language :: JavaScript
License-File: LICENSE
Requires-Dist: six (>=1.10.0)
